{
  "area": "../examples/datasets/shibuya/generated/area.json",
  "property": "../examples/datasets/shibuya/generated/property.json",
  "link": "../examples/datasets/shibuya/generated/link.json",

  "overlay_map": true,
  "origin_lat": 35.6625,
  "origin_lon": 139.70625,
  "offset_x": 0,
  "offset_y": 0,

  "mode": "gps",
  "wind_scale": 1.0,
  "tiles": "OpenStreetMap.Mapnik",
  "zoom": null,

    "markers": [
    {"lat": 35.6625, "lon": 139.70625, "label": "Origin"},
    {"lat": 35.670065, "lon": 139.694966, "label": "Yoyogi Park"}
    ],

  "print_latlon": false,
  "print_shifted_origin": true
}
